{
  "arrow_spacing": {
    "level": "error"
  },

  "braces_spacing": {
    "level": "error",
    "spaces": 0
  },

  "colon_assignment_spacing": {
    "name": "colon_assignment_spacing",
    "level": "error",
    "spacing": {
      "left": 0,
      "right": 1
    }
  },

  "indentation" : {
    "level" : "error",
    "value" : 2
  },

  "cyclomatic_complexity" : {
    "level" : "warn",
    "value" : 11
  },

  "line_endings" : {
    "value" : "unix",
    "level" : "error"
  },

  "newlines_after_classes": {
    "value": 3,
    "level": "error"
  },

  "no_interpolation_in_single_quotes": {
    "name": "no_interpolation_in_single_quotes",
    "level": "error"
  },

  "no_stand_alone_at": {
    "level": "error"
  },

  "no_unnecessary_double_quotes": {
    "name": "no_unnecessary_double_quotes",
    "level": "error"
  },

  "no_debugger": {
    "level": "error",
    "console": true
  },

  "space_operators": {
    "level": "error"
  },

  "spacing_after_comma": {
    "level": "error"
  }
}